[{"children":[{"children":[{"dateAdded":1582782368601,"id":"2792","index":0,"parentId":"2786","title":"【2018年新教材精讲班】华启学院一建通信与广电精讲视频-学习视频教程-培训课程-腾讯课堂","url":"https://ke.qq.com/course/276138"},{"dateAdded":1582782368602,"id":"2793","index":1,"parentId":"2786","title":"职称评审","url":"http://www.xdz.gov.cn/info/20498/198827.htm"},{"dateAdded":1582782368602,"id":"2794","index":2,"parentId":"2786","title":"职称认定","url":"http://www.xdz.gov.cn/info/20498/193205.htm"},{"dateAdded":1582782368602,"id":"2795","index":3,"parentId":"2786","title":"一建报名","url":"http://zg.cpta.com.cn/"},{"dateAdded":1582782368603,"id":"2796","index":4,"parentId":"2786","title":"关于失业保险支持参保企业职工提升职业技能有关问题的通知-西安高新技术产业开发区门户网站","url":"http://www.xdz.gov.cn/Topics/gxsb/20140217/content.jsp?urltype=news.NewsContentUrl&wbtreeid=21640&wbnewsid=181960"},{"dateAdded":1582782368603,"id":"2797","index":5,"parentId":"2786","title":"西安高新区劳动和社会保险网上服务大厅","url":"http://xdzsis.xdz.gov.cn:7317/indexAction.do"},{"dateAdded":1582782368603,"id":"2798","index":6,"parentId":"2786","title":"继续教育学习平台","url":"http://jxjy01.xidian.edu.cn/u/student/training/index.action"},{"dateAdded":1582782368604,"id":"2799","index":7,"parentId":"2786","title":"陕西消防协会-考生报名系统","url":"http://www.sxxfxh.com/"},{"dateAdded":1582782368605,"id":"2800","index":8,"parentId":"2786","title":"西安市人力资源和社会保障局","url":"http://xahrss.xa.gov.cn/fwdt/"},{"dateAdded":1582782368605,"id":"2801","index":9,"parentId":"2786","title":"陕西省专业技术人员继续教育学习平台","url":"http://jxjy01.xidian.edu.cn/newLogin.jsp#"},{"dateAdded":1582782368605,"id":"2802","index":10,"parentId":"2786","title":"西安高新技术产业开发区职称改革工作领导小组办公室关于开展2019年度下半年工程系列中级专业技术职务任职资格评审工作的通知-西安高新技术产业开发区门户网站","url":"http://www.xdz.gov.cn/info/20498/205538.htm"},{"dateAdded":1582782368605,"id":"2803","index":11,"parentId":"2786","title":"西安高新技术产业开发区职称改革工作领导小组办公室关于开展常态化工程系列初、中级职称认定工作的通知-丝路人才网","url":"http://www.xaslrc.com/index.php?m=&c=publicservice&a=news_show&id=251"}],"dateAdded":1582782368582,"dateGroupModified":1582782368605,"id":"2786","index":0,"parentId":"1","title":"exam"},{"children":[{"children":[{"dateAdded":1582782368659,"id":"2929","index":0,"parentId":"2804","title":"陕西省政府采购网","url":"http://www.ccgp-shaanxi.gov.cn/notice/noticeDetail.do?noticeguid=8a85be346b50abc2016b87653b3b37f1"},{"dateAdded":1582782368659,"id":"2930","index":1,"parentId":"2804","title":"陕西省政府采购网","url":"http://www.ccgp-shaanxi.gov.cn/notice/noticeDetail.do?noticeguid=8a85be346b50abc2016b8d7811485886"},{"dateAdded":1582782368659,"id":"2931","index":2,"parentId":"2804","title":"陕西省政府采购网","url":"http://www.ccgp-shaanxi.gov.cn/notice/noticeDetail.do?noticeguid=8a85be336b50abbe016b8d0e59656167"},{"dateAdded":1582782368659,"id":"2932","index":3,"parentId":"2804","title":"陕西省政府采购网","url":"http://www.ccgp-shaanxi.gov.cn/notice/noticeDetail.do?noticeguid=8a85be336b50abbe016b8d0e59656167&tdsourcetag=s_pcqq_aiomsg"}],"dateAdded":1582782368606,"dateGroupModified":1582782368659,"id":"2804","index":0,"parentId":"2787","title":"招标信息"},{"dateAdded":1582782368606,"id":"2805","index":1,"parentId":"2787","title":"陕西省政府采购网","url":"http://www.ccgp-shaanxi.gov.cn/notice/list.do?noticetype=3&index=3&province=province"},{"dateAdded":1582782368606,"id":"2806","index":2,"parentId":"2787","title":"全国公共资源交易平台（陕西省·西安市）","url":"http://xa.sxggzyjy.cn/jydt/001001/001001001/001001001001/subPage.html"},{"dateAdded":1582782368607,"id":"2807","index":3,"parentId":"2787","title":"全国公共资源交易平台（陕西省）陕西省公共资源交易中心","url":"http://www.sxggzyjy.cn/jydt/001001/001001001/001001001001/subPage_jyxx.html"},{"dateAdded":1582782368607,"id":"2808","index":4,"parentId":"2787","title":"陕西采购与招标网","url":"http://39.107.102.206/"},{"dateAdded":1582782368607,"id":"2809","index":5,"parentId":"2787","title":"政府采购-西安高新技术产业开发区门户网站","url":"http://www.xdz.gov.cn/zwgkdiv/lmzl_list_zfcg.jsp?urltype=tree.TreeTempUrl&wbtreeid=20691"},{"dateAdded":1582782368607,"id":"2810","index":6,"parentId":"2787","title":"西安市财政局","url":"http://xaczj.xa.gov.cn/index.htm#"},{"dateAdded":1582782368608,"id":"2811","index":7,"parentId":"2787","title":"庆阳市公共资源交易中心","url":"http://www.qysggzyjy.cn/html/jyInfo/?DISTCODE=621001"},{"dateAdded":1582782368608,"id":"2812","index":8,"parentId":"2787","title":"兰州市公共资源交易中心","url":"http://lzggzyjy.lanzhou.gov.cn/jygk/002002/2.html"},{"dateAdded":1582782368608,"id":"2813","index":9,"parentId":"2787","title":"甘肃省公共资源交易中心","url":"http://ggzyjy.gansu.gov.cn/f/newprovince/annogoods/getListByProjectType"},{"dateAdded":1582782368608,"id":"2814","index":10,"parentId":"2787","title":"甘肃政府采购网","url":"http://www.gszfcg.gansu.gov.cn/"},{"dateAdded":1582782368609,"id":"2815","index":11,"parentId":"2787","title":"甘肃省招标中心有限公司","url":"http://www.gansubidding.com/info/ShowAnnoGoodsList.aspx?ItemID=30"},{"dateAdded":1582782368609,"id":"2816","index":12,"parentId":"2787","title":"宁夏政府采购公共服务平台","url":"http://www.ccgp-ningxia.gov.cn/public/NXGPPNEW/dynamic/index.jsp?id=1"},{"dateAdded":1582782368609,"id":"2817","index":13,"parentId":"2787","title":"宁夏回族自治区公共资源交易网","url":"http://www.nxggzyjy.org/ningxiaweb/002/002001/listPage.html"},{"dateAdded":1582782368610,"id":"2818","index":14,"parentId":"2787","title":"青海省公共资源交易服务平台","url":"http://www.qhggzyjy.gov.cn/fwpt/"},{"dateAdded":1582782368610,"id":"2819","index":15,"parentId":"2787","title":"新疆生产建设兵团公共资源交易信息网","url":"http://ggzy.xjbt.gov.cn/"},{"dateAdded":1582782368611,"id":"2820","index":16,"parentId":"2787","title":"新疆政府采购网","url":"http://www.ccgp-xinjiang.gov.cn/ZcyAnnouncement/index.html"},{"dateAdded":1582782368611,"id":"2821","index":17,"parentId":"2787","title":"新疆政府采购网","url":"http://www.ccgp-xinjiang.gov.cn/home.html"},{"dateAdded":1582782368611,"id":"2822","index":18,"parentId":"2787","title":"乌鲁木齐市政府采购网","url":"http://zfcg.wlmq.gov.cn/login.do?method=beginlogin"},{"dateAdded":1582782368611,"id":"2823","index":19,"parentId":"2787","title":"中招联合招标采购平台","url":"http://www.365trade.com.cn/"},{"dateAdded":1582782368612,"id":"2824","index":20,"parentId":"2787","title":"中国电建集中采购平台","url":"http://ec.powerchina.cn/"},{"dateAdded":1582782368612,"id":"2825","index":21,"parentId":"2787","title":"中国邮政集团公司招标采购平台-首页","url":"http://zgyz.dlzb.com/"},{"dateAdded":1582782368612,"id":"2826","index":22,"parentId":"2787","title":"中国电信集团公司招标采购平台","url":"http://zgdxjt.dlzb.com/"},{"dateAdded":1582782368613,"id":"2827","index":23,"parentId":"2787","title":"中国联通采购与招标网","url":"http://www.chinaunicombidding.cn/jsp/cnceb/web/index_parent.jsp"},{"dateAdded":1582782368613,"id":"2828","index":24,"parentId":"2787","title":"中国移动采购与招标网","url":"https://b2b.10086.cn/b2b/main/preIndex.html"},{"dateAdded":1582782368617,"id":"2829","index":25,"parentId":"2787","title":"中国电信集团采购平台","url":"http://www.ctebuy.com/"},{"dateAdded":1582782368617,"id":"2830","index":26,"parentId":"2787","title":"军队采购网","url":"https://www.plap.cn/"},{"dateAdded":1582782368617,"id":"2831","index":27,"parentId":"2787","title":"中国铁路西安局集团有限公司物资采购商务平台","url":"http://www.xtcgpt.com/mainPageNoticeList.do?method=list&cur=1"},{"dateAdded":1582782368618,"id":"2832","index":28,"parentId":"2787","title":"中国石化物资采购电子商务平台","url":"http://zgsh.sinopec.com/supp/index.shtml"},{"dateAdded":1582782368618,"id":"2833","index":29,"parentId":"2787","title":"中国石油招标投标网 - 网站首页","url":"http://www.cnpcbidding.com/wps/portal/ebid"},{"dateAdded":1582782368619,"id":"2834","index":30,"parentId":"2787","title":"中国中煤能源集团有限公司物资采购电子商务网","url":"http://cg.chinacoal.com:7002/logonAction.do"},{"dateAdded":1582782368619,"id":"2835","index":31,"parentId":"2787","title":"工信部通信工程建设项目招标投标管理信息平台","url":"http://txzb.miit.gov.cn/DispatchAction.do?efFormEname=POIX11"},{"dateAdded":1582782368619,"id":"2836","index":32,"parentId":"2787","title":"中国兵器工业集团公司采购电子商务平台-首页","url":"https://www.norincogroup-ebuy.com/"},{"dateAdded":1582782368619,"id":"2837","index":33,"parentId":"2787","title":"中国华能集团电子商务平台","url":"http://ec.chng.com.cn/ecmall/"},{"dateAdded":1582782368620,"id":"2838","index":34,"parentId":"2787","title":"航天电子采购平台","url":"http://www.ispacechina.com/"},{"dateAdded":1582782368620,"id":"2839","index":35,"parentId":"2787","title":"大唐集团电子商务平台","url":"http://www.cdt-ec.com/home/"},{"dateAdded":1582782368620,"id":"2840","index":36,"parentId":"2787","title":"中国核工业集团公司-电子商务平台","url":"http://ecp.cnnc.com.cn/"},{"dateAdded":1582782368620,"id":"2841","index":37,"parentId":"2787","title":"华润置地招投标","url":"http://srm.crland.com.cn/crland-isp/"},{"dateAdded":1582782368621,"id":"2842","index":38,"parentId":"2787","title":"中航招标网","url":"http://avicbid.com/"},{"dateAdded":1582782368621,"id":"2843","index":39,"parentId":"2787","title":"兵器装备集团招标投标交易平台","url":"http://bingqi.govbuy.cn/"},{"dateAdded":1582782368621,"id":"2844","index":40,"parentId":"2787","title":"苏宁招标与采购平台","url":"http://zb.suning.com/bid-web/main.htm"},{"dateAdded":1582782368621,"id":"2845","index":41,"parentId":"2787","title":"新疆广汇电子采购平台","url":"http://zc.guanghui.com/custom/"},{"dateAdded":1582782368622,"id":"2846","index":42,"parentId":"2787","title":"中国金融集中采购","url":"http://www.cfcpn.com/plist/caigou?pageNo=2&kflag=0&keyword=&keywordType=&province=&city=&typeOne=&ptpTwo="},{"dateAdded":1582782368622,"id":"2847","index":43,"parentId":"2787","title":"招标公告 - 永辉超市","url":"http://www.yonghui.com.cn/2013_zbgg.asp"},{"dateAdded":1582782368623,"id":"2848","index":44,"parentId":"2787","title":"中央政府采购网-电子化政府采购平台","url":"http://www.zycg.gov.cn/"},{"dateAdded":1582782368623,"id":"2849","index":45,"parentId":"2787","title":"中国采购招标网","url":"http://www.chinabidding.cc/"},{"dateAdded":1582782368623,"id":"2850","index":46,"parentId":"2787","title":"中共中央直属机关采购中心","url":"http://zzcg.ccgp.gov.cn/index.jhtml?key=1"},{"dateAdded":1582782368624,"id":"2851","index":47,"parentId":"2787","title":"欢迎访问 国家电网公司电子商务平台","url":"http://ecp.sgcc.com.cn/html/index.html"},{"dateAdded":1582782368624,"id":"2852","index":48,"parentId":"2787","title":"国电招投标网","url":"http://cgdcbidding.com/"},{"dateAdded":1582782368625,"id":"2853","index":49,"parentId":"2787","title":"中国海关政府采购网","url":"http://hgcg.customs.gov.cn/hgcg/"}],"dateAdded":1582782368585,"dateGroupModified":1582782368625,"id":"2787","index":1,"parentId":"1","title":"bid"},{"children":[{"children":[{"dateAdded":1582782368667,"id":"2933","index":0,"parentId":"2854","title":"OpenSIPS/opensips: OpenSIPS is a GPL implementation of a multi-functionality SIP Server that targets to deliver a high-level technical solution (performance, security and quality) to be used in professional SIP server platforms.","url":"https://github.com/OpenSIPS/opensips"},{"dateAdded":1582782368668,"id":"2934","index":1,"parentId":"2854","title":"Peer-to-Peer (P2P) Cloud Computing","url":"https://subutai.io/p2p-cloud.html"},{"dateAdded":1582782368668,"id":"2935","index":2,"parentId":"2854","title":"PJSIP","url":"http://www.pjsip.org/about.htm"},{"dateAdded":1582782368668,"id":"2936","index":3,"parentId":"2854","title":"openSIPS","url":"http://www.opensips.org/Downloads/Downloads"},{"dateAdded":1582782368668,"id":"2937","index":4,"parentId":"2854","title":"GitHub - phodal / awesome-iot：真棒物联网。 关于物联网框架，图书馆，操作系统，平台的大量资源的协作清单","url":"https://github.com/phodal/awesome-iot"},{"dateAdded":1582782368669,"id":"2938","index":5,"parentId":"2854","title":"vzex/dog-tunnel: p2p tunnel,(udp mode work with kcp,https://github.com/skywind3000/kcp)","url":"https://github.com/vzex/dog-tunnel"}],"dateAdded":1582782368626,"dateGroupModified":1582782368669,"id":"2854","index":0,"parentId":"2788","title":"P2P开发"},{"children":[{"dateAdded":1582782368669,"id":"2939","index":0,"parentId":"2855","title":"https://blog.csdn.net/chenlix/article/details/72526205","url":"https://blog.csdn.net/chenlix/article/details/72526205"},{"dateAdded":1582782368669,"id":"2940","index":1,"parentId":"2855","title":"centos7使用yum安装mariaDB（开源MySQL）无法启动的解决办法 - CSDN博客","url":"https://blog.csdn.net/eclothy/article/details/52733891"},{"dateAdded":1582782368669,"id":"2941","index":2,"parentId":"2855","title":"使用windows远程桌面mstsc连接CentOS7系统(通过配置xrdp实现)-Linux-服务器-笨牛网 - 笨牛小白成长之路|技术 教程 分享","url":"https://www.bnxb.com/linuxserver/27459.html"},{"dateAdded":1582782368670,"id":"2942","index":3,"parentId":"2855","title":"Centos 7/1503 - 在安装期间设置基本存储库时出现错误 - 服务器故障","url":"https://serverfault.com/questions/710541/centos-7-1503-getting-error-setting-up-base-repository-during-installation"},{"dateAdded":1582782368675,"id":"2943","index":4,"parentId":"2855","title":"CentOS 7 怎样自动连接网络_百度经验","url":"https://jingyan.baidu.com/article/19192ad8f7c320e53e570728.html"},{"dateAdded":1582782368675,"id":"2944","index":5,"parentId":"2855","title":"CentOS 6、7 安装 Golang - CSDN博客","url":"https://blog.csdn.net/u012724150/article/details/53309522"},{"dateAdded":1582782368675,"id":"2945","index":6,"parentId":"2855","title":"Makefile的使用方法 - linqiaozhou - 博客园","url":"https://www.cnblogs.com/qiaozhoulin/p/4896326.html"},{"dateAdded":1582782368676,"id":"2946","index":7,"parentId":"2855","title":"mysql安装在centos7报错ERROR 1045 (28000): Access denied for user 'root'@'localhost' (using password: NO) - CSDN博客","url":"https://blog.csdn.net/kuluzs/article/details/51924086"},{"dateAdded":1582782368676,"id":"2947","index":8,"parentId":"2855","title":"LAMP一键安装包","url":"https://lamp.sh/"},{"dateAdded":1582782368676,"id":"2948","index":9,"parentId":"2855","title":"解决Navicat连接的时候出现了1045 -Access denied for user'root'@'192.168.37.2'(using password :yes) - CSDN博客","url":"https://blog.csdn.net/u011271894/article/details/51096739"}],"dateAdded":1582782368626,"dateGroupModified":1582782368676,"id":"2855","index":1,"parentId":"2788","title":"Linux"},{"children":[{"dateAdded":1582782368677,"id":"2949","index":0,"parentId":"2856","title":"phpEnv-专业优雅强大的php集成环境","url":"https://www.phpenv.cn/"},{"dateAdded":1582782368677,"id":"2950","index":1,"parentId":"2856","title":"PHPWAMP-最专业的PHP绿色集成环境PHPWAMP/PHPWNMP","url":"http://www.phpwamp.com/"},{"dateAdded":1582782368677,"id":"2951","index":2,"parentId":"2856","title":"Dric / simple-photos-contest：一个用PHP编写的简单照片竞赛画廊","url":"https://github.com/Dric/simple-photos-contest"}],"dateAdded":1582782368626,"dateGroupModified":1582782368677,"id":"2856","index":2,"parentId":"2788","title":"php"},{"children":[{"dateAdded":1582782368678,"id":"2952","index":0,"parentId":"2857","title":"Hugo 0.37: Preserve PNG Colour Palette | Hugo","url":"http://gohugo.io/news/0.37-relnotes/"},{"dateAdded":1582782368678,"id":"2953","index":1,"parentId":"2857","title":"lightGallery: Dynamic","url":"https://sachinchoolur.github.io/lightgallery.js/demos/dynamic.html"},{"dateAdded":1582782368679,"id":"2954","index":2,"parentId":"2857","title":"Syncthing","url":"https://syncthing.net/"},{"dateAdded":1582782368679,"id":"2955","index":3,"parentId":"2857","title":"Xdebug - Chrome Web Store","url":"https://chrome.google.com/webstore/detail/xdebug/nhodjblplijafdpjjfhhanfmchplpfgl/related?hl=en-GB&gl=GB"}],"dateAdded":1582782368626,"dateGroupModified":1582782368679,"id":"2857","index":3,"parentId":"2788","title":"开发"},{"children":[{"dateAdded":1582782368679,"id":"2956","index":0,"parentId":"2858","title":"你会做Web上的用户登录功能吗？ – 酷 壳 – CoolShell","url":"https://coolshell.cn/articles/5353.html"},{"dateAdded":1582782368679,"id":"2957","index":1,"parentId":"2858","title":"模块 - 廖雪峰的官方网站","url":"https://www.liaoxuefeng.com/wiki/1016959663602400/1017454145014176"},{"dateAdded":1582782368679,"id":"2958","index":2,"parentId":"2858","title":"清华大学 TUNA 协会 - Events","url":"https://tuna.moe/events/"},{"dateAdded":1582782368680,"id":"2959","index":3,"parentId":"2858","title":"标准网","url":"https://www.biaozhun.org/"},{"dateAdded":1582782368680,"id":"2960","index":4,"parentId":"2858","title":"Segoe MDL2 icon guidelines - Windows UWP applications | Microsoft Docs","url":"https://docs.microsoft.com/en-us/windows/uwp/design/style/segoe-ui-symbol-font"},{"dateAdded":1582782368680,"id":"2961","index":5,"parentId":"2858","title":"Netcraft | Internet Research, Cybercrime Disruption and PCI Security Services","url":"https://www.netcraft.com/"},{"dateAdded":1582782368681,"id":"2962","index":6,"parentId":"2858","title":"Site report for https://www.eee-eee.com | Netcraft","url":"https://sitereport.netcraft.com/?url=https%3A%2F%2Fwww.eee-eee.com%2F"}],"dateAdded":1582782368626,"dateGroupModified":1582782368681,"id":"2858","index":4,"parentId":"2788","title":"博客/网站"},{"children":[{"dateAdded":1582782368682,"id":"2963","index":0,"parentId":"2859","title":"STM32F4_引领入门 - strongerHuang - 博客园","url":"https://www.cnblogs.com/strongerHuang/p/5605228.html"},{"dateAdded":1582782368682,"id":"2964","index":1,"parentId":"2859","title":"如何使用STM32CubeMX配置ETH（RMII） - CSDN博客","url":"https://blog.csdn.net/xukao5671927/article/details/53306137"},{"dateAdded":1582782368682,"id":"2965","index":2,"parentId":"2859","title":"开发板入门","url":"https://ke.qq.com/webcourse/index.html#course_id=279403&term_id=100330877&taid=1965316905386859&vid=r1423w3ba05"},{"dateAdded":1582782368683,"id":"2966","index":3,"parentId":"2859","title":"stm32 以太网 LWIP TFTP IAP 远程升级 - CSDN博客","url":"https://blog.csdn.net/u012246376/article/details/53228072"},{"dateAdded":1582782368683,"id":"2967","index":4,"parentId":"2859","title":"LwIP之socket应用--WebServer和Modbus TCP - 啊哈彭 - 博客园","url":"https://www.cnblogs.com/pingwen/p/6684659.html"},{"dateAdded":1582782368683,"id":"2968","index":5,"parentId":"2859","title":"CGI详解（原理，配置及访问） - CSDN博客","url":"https://blog.csdn.net/liunian_siyu/article/details/60964966"},{"dateAdded":1582782368684,"id":"2969","index":6,"parentId":"2859","title":"STM32IAP升级------IAP升级功能编写初期的一些困惑与疑问---完成功能后的总结 - CSDN博客","url":"https://blog.csdn.net/super_demo/article/details/32133257"},{"dateAdded":1582782368685,"id":"2970","index":7,"parentId":"2859","title":"Cortex_M3平台上lwIP_AJAX的Web嵌入式应用 - 道客巴巴","url":"http://www.doc88.com/p-1166523430295.html"},{"dateAdded":1582782368685,"id":"2971","index":8,"parentId":"2859","title":"行业知识 :: 枫叶在线帮助","url":"http://support.senboll.com:8888/help/0-standard/basic-knowledge/"},{"dateAdded":1582782368685,"id":"2972","index":9,"parentId":"2859","title":"phpMyAdmin","url":"http://192.168.8.4/mysqladmin/"}],"dateAdded":1582782368627,"dateGroupModified":1582782368685,"id":"2859","index":5,"parentId":"2788","title":"ARM开发"},{"children":[{"dateAdded":1582782368685,"id":"2973","index":0,"parentId":"2860","title":"采用Algolia作为Hugo搜索方案 | Blog折腾小记（6）","url":"https://withdewhua.space/2018/11/23/search-with-algolia-in-hugo/"},{"dateAdded":1582782368686,"id":"2974","index":1,"parentId":"2860","title":"使用Hugo + Algolia进行静态网站搜索| Forestry.io","url":"https://forestry.io/blog/search-with-algolia-in-hugo/"},{"dateAdded":1582782368686,"id":"2975","index":2,"parentId":"2860","title":"新标签页","url":"chrome://newtab/"},{"dateAdded":1582782368686,"id":"2976","index":3,"parentId":"2860","title":"Hugo 集成 Algolia 搜索 - 后端 - 掘金","url":"https://juejin.im/entry/5ab6e9c8f265da239d4943c6"}],"dateAdded":1582782368627,"dateGroupModified":1582782368686,"id":"2860","index":6,"parentId":"2788","title":"hugo-website"},{"children":[{"dateAdded":1582782368686,"id":"2977","index":0,"parentId":"2861","title":"HomeAssistant智能家居实战篇 - 网易云课堂","url":"https://study.163.com/course/courseLearn.htm?courseId=1006189053#/learn/video?lessonId=1053678440&courseId=1006189053"},{"dateAdded":1582782368687,"id":"2978","index":1,"parentId":"2861","title":"vs code ssh远程连接树莓派_MacwinWin的博客-CSDN博客","url":"https://blog.csdn.net/MacwinWin/article/details/101519016"},{"dateAdded":1582782368687,"id":"2979","index":2,"parentId":"2861","title":"ParadoxAlarmInterface","url":"https://github.com/ParadoxAlarmInterface"},{"dateAdded":1582782368687,"id":"2980","index":3,"parentId":"2861","title":"Home Assistant","url":"http://support.senboll.com:8123/hassio"},{"dateAdded":1582782368687,"id":"2981","index":4,"parentId":"2861","title":"http://192.168.8.25:8123/hassio","url":"http://192.168.8.25:8123/hassio"},{"dateAdded":1582782368687,"id":"2982","index":5,"parentId":"2861","title":"有道云笔记","url":"https://note.youdao.com/ynoteshare1/index.html?id=54a03abe4f949be25bddd34c0f3f016d&type=note"},{"dateAdded":1582782368688,"id":"2983","index":6,"parentId":"2861","title":"有道云笔记","url":"https://note.youdao.com/ynoteshare1/index.html?id=a1dea97e214a746d9608716c663ee5ec&type=note"},{"dateAdded":1582782368688,"id":"2984","index":7,"parentId":"2861","title":"获取镜像 | Docker 从入门到实践","url":"https://vuepress.mirror.docker-practice.com/image/pull.html#%E8%BF%90%E8%A1%8C"},{"dateAdded":1582782368688,"id":"2985","index":8,"parentId":"2861","title":"树莓派上homeassistant与hassio双系统共存 - HAChina 中文网","url":"https://www.hachina.io/9667.html"},{"dateAdded":1582782368688,"id":"2986","index":9,"parentId":"2861","title":"ParadoxAlarmInterface/pai: Paradox Magellan, Spectra and EVO, with MQTT, Signal, Pushbullet, Pushover and others","url":"https://github.com/ParadoxAlarmInterface/pai"},{"dateAdded":1582782368689,"id":"2987","index":10,"parentId":"2861","title":"http://support.senboll.com:8123/hassio","url":"http://support.senboll.com:8123/hassio/dashboard"}],"dateAdded":1582782368627,"dateGroupModified":1582782368689,"id":"2861","index":7,"parentId":"2788","title":"rpi"},{"children":[{"dateAdded":1582782368689,"id":"2988","index":0,"parentId":"2862","title":"收集最全的Joomla教材网站和joomla模板网站-云栖社区-阿里云","url":"https://yq.aliyun.com/articles/564994"},{"dateAdded":1582782368689,"id":"2989","index":1,"parentId":"2862","title":"Free Joomla Templates","url":"http://www.joomlaperfect.com/"},{"dateAdded":1582782368689,"id":"2990","index":2,"parentId":"2862","title":"22 Business Joomla Templates","url":"https://www.joomdev.com/products/templates?tag=Business"},{"dateAdded":1582782368690,"id":"2991","index":3,"parentId":"2862","title":"Joomla建站/定制/服务与支持","url":"https://www.joomlass.com/"},{"dateAdded":1582782368691,"id":"2992","index":4,"parentId":"2862","title":"JOOMLA视频教程 - Joomla!服务与支持","url":"https://www.joomlass.com/joomla-tutorial/joomla-video"},{"dateAdded":1582782368691,"id":"2993","index":5,"parentId":"2862","title":"Joomla!设计/定制/开发/企业应用 - 六艺Joomla建站","url":"https://www.eee-eee.com/"},{"dateAdded":1582782368692,"id":"2994","index":6,"parentId":"2862","title":"www.joomlart.com","url":"https://www.joomlart.com/member/downloads/joomlart/free-templates/ja-stark"},{"dateAdded":1582782368692,"id":"2995","index":7,"parentId":"2862","title":"Joomla 2.5 多语言网站的设计 - 宁皓网","url":"https://ninghao.net/blog/365"},{"dateAdded":1582782368693,"id":"2996","index":8,"parentId":"2862","title":"Joomla - T3模板（非常好用的4屏响应式模板） - magicK - 博客园","url":"https://www.cnblogs.com/elfpower/p/10063921.html"},{"dateAdded":1582782368694,"id":"2997","index":9,"parentId":"2862","title":"Getting Started | Joomla Templates and Extensions Provider","url":"https://www.joomlart.com/documentation/t4-framework/getting-started"},{"dateAdded":1582782368694,"id":"2998","index":10,"parentId":"2862","title":"Astroid Joomla框架-＃1 Joomla模板框架","url":"https://demo.joomdev.com/astroid-framework/?utm_source=astroid_framework_home#"},{"dateAdded":1582782368694,"id":"2999","index":11,"parentId":"2862","title":"Astroid – User Manual – JoomDev Documentation","url":"https://docs.joomdev.com/category/astroid-user-manual/"}],"dateAdded":1582782368627,"dateGroupModified":1582782368694,"id":"2862","index":8,"parentId":"2788","title":"joomla"},{"children":[{"dateAdded":1582782368695,"id":"3000","index":0,"parentId":"2863","title":"Drupal China | Drupal中文社区","url":"http://drupalchina.cn/"},{"dateAdded":1582782368696,"id":"3001","index":1,"parentId":"2863","title":"https://www.drupal.org","url":"https://www.drupal.org/"},{"dateAdded":1582782368696,"id":"3002","index":2,"parentId":"2863","title":"BUSINESS+ Lite | MORE THAN (Just) THEMES","url":"https://morethanthemes.com/themes/businessplus-lite"},{"dateAdded":1582782368696,"id":"3003","index":3,"parentId":"2863","title":"https://ranqiangjun.gitbooks.io/the-drupal-8-theming-guide/content/","url":"https://ranqiangjun.gitbooks.io/the-drupal-8-theming-guide/content/"},{"dateAdded":1582782368696,"id":"3004","index":4,"parentId":"2863","title":"水滴间 | 云客drupal官方网站","url":"http://www.indrupal.com/"},{"dateAdded":1582782368697,"id":"3005","index":5,"parentId":"2863","title":"Introduction | Drupal 8 主题开发指南中文版","url":"https://ranqiangjun.gitbooks.io/the-drupal-8-theming-guide/content/"},{"dateAdded":1582782368697,"id":"3006","index":6,"parentId":"2863","title":"Home | Ran Qiangjun","url":"https://ranqiangjun.com/"},{"dateAdded":1582782368697,"id":"3007","index":7,"parentId":"2863","title":"https://ranqiangjun.com/","url":"https://ranqiangjun.com/"},{"dateAdded":1582782368698,"id":"3008","index":8,"parentId":"2863","title":"Drupal 8 Theme folder structure | Drupal 8 guide on Drupal.org","url":"https://www.drupal.org/docs/8/theming-drupal-8/drupal-8-theme-folder-structure"},{"dateAdded":1582782368698,"id":"3009","index":9,"parentId":"2863","title":"首页 | Drupal模块中文社区","url":"http://www.drupalmodule.cn/"},{"dateAdded":1582782368698,"id":"3010","index":10,"parentId":"2863","title":"Nick | Now I Code","url":"http://www.nowicode.com/user/99"},{"dateAdded":1582782368699,"id":"3011","index":11,"parentId":"2863","title":"下载 | 水滴间 | 云客drupal官方网站","url":"http://www.indrupal.com/download"},{"dateAdded":1582782368700,"id":"3012","index":12,"parentId":"2863","title":"Drupal8主题开发 - 网易云课堂","url":"https://study.163.com/course/courseLearn.htm?courseId=1003588003#/learn/video?lessonId=1004586883&courseId=1003588003"},{"dateAdded":1582782368700,"id":"3013","index":13,"parentId":"2863","title":"什么是drupal8主题，为什么要创建drupal主题 - Durpal和前端开发视频教程","url":"http://www.tvdrupal.com/detail-393.html"}],"dateAdded":1582782368627,"dateGroupModified":1582782368700,"id":"2863","index":9,"parentId":"2788","title":"drupal"},{"dateAdded":1582782368627,"id":"2864","index":10,"parentId":"2788","title":"查看字符编码（UTF-8）","url":"http://www.mytju.com/classcode/tools/encode_utf8.asp"},{"dateAdded":1582782368628,"id":"2865","index":11,"parentId":"2788","title":"想了解浏览器内核，看这一篇就够了 - 密密缝 - 博客园","url":"https://www.cnblogs.com/mimifeng/p/9542404.html"},{"dateAdded":1582782368628,"id":"2866","index":12,"parentId":"2788","title":"Free Online Font Converter","url":"http://www.freefontconverter.com/"},{"dateAdded":1582782368628,"id":"2867","index":13,"parentId":"2788","title":"Research by Kirils Solovjovs","url":"https://kirils.org/"},{"dateAdded":1582782368628,"id":"2868","index":14,"parentId":"2788","title":"Youtube视频下载 - 免费在线 YouTube 下载器","url":"https://zh.savefrom.net/"},{"dateAdded":1582782368629,"id":"2869","index":15,"parentId":"2788","title":"Online converter - convert video, images, audio and documents for free","url":"https://www.online-convert.com/"},{"dateAdded":1582782368629,"id":"2870","index":16,"parentId":"2788","title":"联通光猫wo-27s拨号模式,路由模式,桥接模式及改了宽带密码上不了网解决方法-电脑技术-网虫小王工作室","url":"https://www.wwc-blog.com/post/416.html"},{"dateAdded":1582782368629,"id":"2871","index":17,"parentId":"2788","title":"Drupal 8 User Guide | Drupal 8 User Guide guide on Drupal.org","url":"https://www.drupal.org/docs/user_guide/en/index.html"},{"dateAdded":1582782368629,"id":"2872","index":18,"parentId":"2788","title":"导航栏 · Bootstrap","url":"http://code.z01.com/v4/components/navbar.html"},{"dateAdded":1582789439329,"id":"3026","index":19,"parentId":"2788","title":"Font Awesome 中文网 – | 字体图标","url":"http://www.fontawesome.com.cn/"},{"dateAdded":1582967027884,"id":"3028","index":20,"parentId":"2788","title":"雷锋网_读懂智能&未来","url":"https://www.leiphone.com/us/rss"},{"dateAdded":1582967354799,"id":"3029","index":21,"parentId":"2788","title":"中新网RSS频道聚合","url":"http://www.chinanews.com/rss/index.shtml"}],"dateAdded":1582782368585,"dateGroupModified":1582967354799,"id":"2788","index":2,"parentId":"1","title":"tech"},{"children":[{"dateAdded":1582782368629,"id":"2873","index":0,"parentId":"2789","title":"网络科技PPT模板_网络科技PPT背景图片下载 - 优品PPT","url":"http://www.ypppt.com/moban/kexue/"},{"dateAdded":1582782368630,"id":"2874","index":1,"parentId":"2789","title":"下载 Creative Cloud 应用程序","url":"https://helpx.adobe.com/cn/download-install/kb/creative-cloud-apps-download.html"},{"dateAdded":1582782368630,"id":"2875","index":2,"parentId":"2789","title":"adobe 下载","url":"https://chavzc5-my.sharepoint.com/personal/vposy_eiz_me/_layouts/15/onedrive.aspx"}],"dateAdded":1582782368586,"dateGroupModified":1582782368630,"id":"2789","index":3,"parentId":"1","title":"design"},{"children":[{"children":[{"dateAdded":1582782368701,"id":"3014","index":0,"parentId":"2876","title":"陕西采购与招标网","url":"http://bulletin.sntba.com/biddingBulletin/2019-11-20/143821.html"}],"dateAdded":1582782368630,"dateGroupModified":1582782368701,"id":"2876","index":0,"parentId":"2790","title":"招标公告"},{"children":[{"dateAdded":1582782368701,"id":"3015","index":0,"parentId":"2877","title":"西安环太科技发展有限公司 冯耀辉 13109580803","url":"http://huan-tai.com/lxwm"},{"dateAdded":1582782368701,"id":"3016","index":1,"parentId":"2877","title":"陕西省政府采购网","url":"http://ccgp-shaanxi.gov.cn/notice/noticeDetail.do?noticeguid=BA122A790D8642769C87455C83EA98E4"},{"dateAdded":1582782368702,"id":"3017","index":2,"parentId":"2877","title":"安防弱电工程_酒店视频网络弱电监控_建筑智能化综合布线_智能公厕安防控制_西安智桦物联网信息技术有限公司","url":"http://www.xazhwl.cn/"}],"dateAdded":1582782368630,"dateGroupModified":1582782368702,"id":"2877","index":1,"parentId":"2790","title":"潜在客户"},{"children":[{"dateAdded":1582782368702,"id":"3018","index":0,"parentId":"2878","title":"您有新消息","url":"https://www.drzk.cn/plus/list.php?tid=26"},{"dateAdded":1582782368702,"id":"3019","index":1,"parentId":"2878","title":"河南省美一电子科技有限公司","url":"http://www.hnmyaf.com/product1.asp?fid=69"},{"dateAdded":1582782368703,"id":"3020","index":2,"parentId":"2878","title":"Benvenuti nella nuova dimensione della Sicurezza e Domotica","url":"https://www.kseniasecurity.com/en"},{"dateAdded":1582782368703,"id":"3021","index":3,"parentId":"2878","title":"driverCentral Help Desk","url":"https://help.drivercentral.io/"},{"dateAdded":1582782368703,"id":"3022","index":4,"parentId":"2878","title":"KNX中国用户组织委员会","url":"http://www.knxchina.org/"},{"dateAdded":1582782368703,"id":"3023","index":5,"parentId":"2878","title":"意林电锁-全球领先的电锁器材制造商及著名安防品牌","url":"http://www.yli.cn/"},{"dateAdded":1582782368704,"id":"3024","index":6,"parentId":"2878","title":"Cellular communicator G16 - Trikdis","url":"https://www.trikdis.com/en/alarm-communicators/cellular-alarm-communicators/cellular-communicator-g16/"},{"dateAdded":1582782368704,"id":"3025","index":7,"parentId":"2878","title":"How Protegus works","url":"https://www.protegus.eu/en/features"}],"dateAdded":1582782368630,"dateGroupModified":1582789439329,"id":"2878","index":2,"parentId":"2790","title":"供应商"},{"dateAdded":1582782368631,"id":"2879","index":3,"parentId":"2790","title":"产品登记查询系统","url":"http://support.senboll.com:99/account"},{"dateAdded":1582782368631,"id":"2880","index":4,"parentId":"2790","title":"枫叶相册","url":"http://support.senboll.com:8888/usage"},{"dateAdded":1582782368632,"id":"2881","index":5,"parentId":"2790","title":"枫叶驱动授权官网","url":"http://support.senboll.com:8888/codepay/"},{"dateAdded":1582782368632,"id":"2882","index":6,"parentId":"2790","title":"驱动(对接Control4)说明书","url":"http://support.senboll.com:8888/help/node2/paradox-to-control4-driver/"},{"dateAdded":1582782368633,"id":"2883","index":7,"parentId":"2790","title":"主页-枫叶在线帮助","url":"http://support.senboll.com:8888/help/"},{"dateAdded":1582782368633,"id":"2884","index":8,"parentId":"2790","title":"首页-枫叶在线帮助 - 127.0.0.1","url":"http://127.0.0.1:1313/help/"},{"dateAdded":1582782368634,"id":"2885","index":9,"parentId":"2790","title":"枫叶资料服务器","url":"http://support.senboll.com:8888/index.php?user/login"},{"dateAdded":1582782368634,"id":"2886","index":10,"parentId":"2790","title":"枫叶资料服务器-lan","url":"http://192.168.8.8:8888/help"},{"dateAdded":1582782368634,"id":"2887","index":11,"parentId":"2790","title":"Senboll ERP","url":"http://support.senboll.com:81/"},{"dateAdded":1582782368635,"id":"2888","index":12,"parentId":"2790","title":"Senboll ERP - 192.168.8.8:81","url":"http://192.168.8.8:81/index.php?mainmenu=home"},{"dateAdded":1582782368636,"id":"2889","index":13,"parentId":"2790","title":"Senboll ERP - 127.0.0.1:81","url":"http://127.0.0.1:81/"},{"dateAdded":1582782368636,"id":"2890","index":14,"parentId":"2790","title":"Dolibarr ERP CRM Wiki","url":"https://wiki.dolibarr.org/index.php/Main_Page"},{"dateAdded":1582782368643,"id":"2891","index":15,"parentId":"2790","title":"Golang系列（九）之模板语法 - 胡伟煌的博客 - CSDN博客","url":"https://blog.csdn.net/huwh_/article/details/77140664"},{"dateAdded":1582782368644,"id":"2892","index":16,"parentId":"2790","title":"Online regex tester and debugger: PHP, PCRE, Python, Golang and JavaScript","url":"https://regex101.com/"},{"dateAdded":1582782368644,"id":"2893","index":17,"parentId":"2790","title":"GitHub - Dolibarr/dolibarr: Dolibarr ERP CRM is a modern software package to manage your company or foundation activity (contacts, suppliers, invoices, orders, stocks, agenda, ...).It's opensource software (wrote with PHP language) designed for small and ","url":"https://github.com/dolibarr/dolibarr"},{"dateAdded":1582782368645,"id":"2894","index":18,"parentId":"2790","title":"mysqladmin - 192.168.8.8","url":"http://192.168.8.8/mysqladmin"},{"dateAdded":1582782368645,"id":"2895","index":19,"parentId":"2790","title":"phpMyAdmin","url":"http://localhost:8080/mysqladmin/"},{"dateAdded":1582782368645,"id":"2896","index":20,"parentId":"2790","title":"mysqladmin 127.0.0.1","url":"http://127.0.0.1/mysqladmin"},{"dateAdded":1582782368646,"id":"2897","index":21,"parentId":"2790","title":"com.paradox.gold","url":"https://play.google.com/store/apps/details?id=com.paradox.gold"},{"dateAdded":1582782368646,"id":"2898","index":22,"parentId":"2790","title":"Templates | Hugo","url":"https://gohugo.io/templates/"},{"dateAdded":1582782368646,"id":"2899","index":23,"parentId":"2790","title":"Paradox - Headquarters","url":"https://www.paradox.com/"},{"dateAdded":1582782368646,"id":"2900","index":24,"parentId":"2790","title":"Paradox Support","url":"https://support.paradox.com/index.php"},{"dateAdded":1582782368646,"id":"2901","index":25,"parentId":"2790","title":"Senboll OA","url":"http://192.168.96.101/sbl/"},{"dateAdded":1582782368647,"id":"2902","index":26,"parentId":"2790","title":"“support.senboll.com:81”国内多个地点网站测速结果--网站测速--站长工具","url":"http://tool.chinaz.com/speedtest/support.senboll.com:81"},{"dateAdded":1582782368647,"id":"2903","index":27,"parentId":"2790","title":"Paradox Support","url":"https://support.paradox.com/tickets.php"}],"dateAdded":1582782368586,"dateGroupModified":1582782368647,"id":"2790","index":4,"parentId":"1","title":"senboll"},{"children":[{"dateAdded":1582782368647,"id":"2904","index":0,"parentId":"2791","title":"国家企业信用信息公示系统","url":"http://www.gsxt.gov.cn/index.html"},{"dateAdded":1582782368648,"id":"2905","index":1,"parentId":"2791","title":"下载通信Android应用程序APK - APKTurbo","url":"https://www.apkturbo.com/apps/communication/"},{"dateAdded":1582782368648,"id":"2906","index":2,"parentId":"2791","title":"首页-西安高新技术产业开发区门户网站","url":"http://www.xdz.gov.cn/Topics/aagzf/index.jsp?urltype=tree.TreeTempUrl&wbtreeid=21742"},{"dateAdded":1582782368649,"id":"2907","index":3,"parentId":"2791","title":"陕西省安防协会网站","url":"http://www.sxafxh.cn/qttz/1091897652074909697.html"},{"dateAdded":1582782368649,"id":"2908","index":4,"parentId":"2791","title":"西安市住房保障和房屋管理局_政务公开","url":"http://fgj.xa.gov.cn/zw/List.aspx?firsttypeid=4&secondtypeid=18&thirdtypeid=206"},{"dateAdded":1582782368649,"id":"2909","index":5,"parentId":"2791","title":"西安市商品住房认购登记平台","url":"http://zfyxdj.xa.gov.cn/zfrgdjpt/index.html"},{"dateAdded":1582782368649,"id":"2910","index":6,"parentId":"2791","title":"西安商品住房价格公示信息","url":"http://117.39.29.75:8085/pricePublic/house/public/index"},{"dateAdded":1582782368650,"id":"2911","index":7,"parentId":"2791","title":"沣东新城商品住房意向登记平台","url":"http://111.20.241.194:801/zfrgdjpt/xmgs.aspx"},{"dateAdded":1582782368650,"id":"2912","index":8,"parentId":"2791","title":"西咸新区商品房价格公示","url":"http://www.xixianxinqu.gov.cn/info/iList.jsp?cat_id=10045&tm_id=27"},{"dateAdded":1582782368650,"id":"2913","index":9,"parentId":"2791","title":"Google地图","url":"http://www.google.cn/maps/@35.780287,104.1374349,4z"},{"dateAdded":1582782368650,"id":"2914","index":10,"parentId":"2791","title":"百度地图","url":"https://map.baidu.com/"},{"dateAdded":1582782368651,"id":"2915","index":11,"parentId":"2791","title":"高德地图","url":"https://www.amap.com/"},{"dateAdded":1582782368651,"id":"2916","index":12,"parentId":"2791","title":"腾讯地图","url":"https://map.qq.com/"},{"dateAdded":1582782368651,"id":"2917","index":13,"parentId":"2791","title":"Insite Gold 2.5.0 APK - com.paradox.gold APK Download","url":"https://apkplz.net/app/com.paradox.gold"},{"dateAdded":1582782368652,"id":"2918","index":14,"parentId":"2791","title":"小米开放平台","url":"https://dev.mi.com/user?userId=1338332629"},{"dateAdded":1582782368652,"id":"2919","index":15,"parentId":"2791","title":"华为开发者联盟","url":"https://developer.huawei.com/consumer/cn/console#/serviceCards/AppService"},{"dateAdded":1582782368652,"id":"2920","index":16,"parentId":"2791","title":"360移动开放平台-助力开发者腾飞","url":"http://dev.360.cn/mod3/mobilenavs/index?qid=3084606064#"},{"dateAdded":1582782368652,"id":"2921","index":17,"parentId":"2791","title":"腾讯开放平台 OPEN.QQ.COM","url":"https://user.open.qq.com/userv2/info"},{"dateAdded":1582782368653,"id":"2922","index":18,"parentId":"2791","title":"广东政务服务网统一身份认证平台","url":"http://tyrz.gdbs.gov.cn/am/login/initAuth.do?gotoUrl=http%3A%2F%2Ftyrz.gdbs.gov.cn%2Fam%2Foauth2%2Fauthorize%3Fservice%3DinitService%26client_id%3Dgdbsszgrbxfw%26client_secret%3Dszgs20181012%26scope%3Dall%26response_type%3Dcode%26redirect_uri%3Dhttps%253A%252F%252Fsipub.sz.gov.cn%252Fhspms%252Flogon.do%253Fmethod%253DgdCasCallback%2526sxbm%253DreturnZy"},{"dateAdded":1582782368653,"id":"2923","index":19,"parentId":"2791","title":"华为商城","url":"https://www.vmall.com/member/order-11510180904"},{"dateAdded":1582782368654,"id":"2924","index":20,"parentId":"2791","title":"域名控制面板","url":"http://dns.4cun.com/jiexi.asp"},{"dateAdded":1582782368656,"id":"2925","index":21,"parentId":"2791","title":"快递网点查询 - 快递100","url":"https://www.kuaidi100.com/network/"},{"dateAdded":1582782368657,"id":"2926","index":22,"parentId":"2791","title":"中央气象台网站启用新域名www.nmc.cn","url":"http://www.nmc.cn/"},{"dateAdded":1582782368657,"id":"2927","index":23,"parentId":"2791","title":"求助：如何隐藏无权限访问的共享文件夹？","url":"https://social.technet.microsoft.com/Forums/zh-CN/ae043512-656c-4c19-932a-8652f475c5b1/27714211616530622914203093854434255260802643538480357753838230?forum=windowsserversystemzhchs"},{"dateAdded":1582782368658,"id":"2928","index":24,"parentId":"2791","title":"OpenStreetMap","url":"https://www.openstreetmap.org/#map=11/35.5160/107.2987"}],"dateAdded":1582782368586,"dateGroupModified":1582782368658,"id":"2791","index":5,"parentId":"1","title":"已导入"}],"dateAdded":1518058543509,"dateGroupModified":1582782368587,"id":"1","index":0,"parentId":"0","title":"书签栏"}]